config/__init__.py
config/asgi.py
config/settings.py
config/urls.py
config/wsgi.py
msgs/__init__.py
msgs/admin.py
msgs/app.py
msgs/exceptions.py
msgs/helpers.py
msgs/mixins.py
msgs/models.py
msgs/signals.py
msgs/tests.py
msgs/utils.py
msgs/views.py
msgs/abstract/__init__.py
msgs/abstract/admin.py
msgs/abstract/models.py
msgs/migrations/0001_initial.py
msgs/migrations/0002_timestamped_messages.py
msgs/migrations/0003_provider_fields_and_statuses.py
msgs/migrations/0004_default_templates_datamigration.py
msgs/migrations/0005_tpl_name_and_type.py
msgs/migrations/0006_tpl_fields_changed.py
msgs/migrations/0007_auto_20210715_1608.py
msgs/migrations/0008_auto_20210825_1250.py
msgs/migrations/0009_auto_20220206_1105.py
msgs/migrations/0010_auto_20220328_1109.py
msgs/migrations/0011_auto_20220613_0857.py
msgs/migrations/__init__.py
msgs/providers/__init__.py
msgs/providers/base.py
msgs/providers/dummy.py
msgs/providers/plivo.py
msgs/providers/sendgrid.py
msgs/providers/sendinblue.py
msgs/providers/sendinblue_sdk.py
msgs/providers/sendpulse.py
msgs/providers/telegram.py
msgs/providers/twilio.py
msgs/providers/voximplant.py
django_msgs-1.3.26.dist-info/LICENSE
django_msgs-1.3.26.dist-info/METADATA
django_msgs-1.3.26.dist-info/WHEEL
django_msgs-1.3.26.dist-info/top_level.txt
django_msgs-1.3.26.dist-info/RECORD
