Metadata-Version: 2.1
Name: django-msgs
Version: 1.3.26
Summary: Emails and SMSs managing framework for Django
Home-page: https://github.com/san4ezy/django_msgs
Author: Alexander Yudkin
Author-email: san4ezy@gmail.com
License: UNKNOWN
Platform: UNKNOWN
Classifier: Environment :: Web Environment
Classifier: Framework :: Django
Classifier: Intended Audience :: Developers
Classifier: Operating System :: OS Independent
Classifier: Programming Language :: Python
Classifier: Topic :: Software Development :: Libraries :: Python Modules
Requires-Python: >=3.6
Requires-Dist: django-json-widget
